MANIFEST.in
README.rst
setup.py
mathx2/__init__.py
mathx2.egg-info/PKG-INFO
mathx2.egg-info/SOURCES.txt
mathx2.egg-info/dependency_links.txt
mathx2.egg-info/top_level.txt