Metadata-Version: 2.1
Name: mathx2
Version: 1.0.2
Summary: Basic math functions
Home-page: UNKNOWN
Author: mathx2
Author-email: malgo.rzata.woz.niak.1999@interia.pl
License: MIT
Keywords: functions math
Platform: UNKNOWN
Classifier: Development Status :: 5 - Production/Stable
Classifier: Intended Audience :: Education
Classifier: Operating System :: Microsoft :: Windows :: Windows 10
Classifier: License :: OSI Approved :: MIT License
Classifier: Programming Language :: Python :: 3
